jupyter_extension_publish/__init__.py
jupyter_extension_publish/config.py
jupyter_extension_publish/handlers.py
jupyter_extension_publish/static/index.js
jupyter_extension_publish-0.4.dist-info/LICENSE
jupyter_extension_publish-0.4.dist-info/METADATA
jupyter_extension_publish-0.4.dist-info/WHEEL
jupyter_extension_publish-0.4.dist-info/top_level.txt
jupyter_extension_publish-0.4.dist-info/RECORD
