Metadata-Version: 2.1
Name: jupyter-extension-publish
Version: 0.4
Summary: jupyter extension for publish notebook
Home-page: UNKNOWN
Author: Keunhui Park
Author-email: keunhui.park@gmail.com
License: UNKNOWN
Platform: UNKNOWN
Requires-Dist: ipython (>=4)
Requires-Dist: notebook (>=4.3.1)
Requires-Dist: jupyter
Requires-Dist: boto3
